src/mcp_server_collector/__init__.py
src/mcp_server_collector/extract.py
src/mcp_server_collector/fetch.py
src/mcp_server_collector/prompts.py
src/mcp_server_collector/server.py
src/mcp_server_collector/submit.py
orange_mcp_server_collector-0.1.0.dist-info/METADATA
orange_mcp_server_collector-0.1.0.dist-info/WHEEL
orange_mcp_server_collector-0.1.0.dist-info/entry_points.txt
orange_mcp_server_collector-0.1.0.dist-info/RECORD
