Metadata-Version: 2.4
Name: orange-mcp-server-collector
Version: 0.1.0
Summary: A MCP Server used to collect MCP Servers over the internet.
Author-email: idoubi <me@idoubi.cc>
Requires-Python: >=3.12
Requires-Dist: aiohttp>=3.11.10
Requires-Dist: mcp>=1.1.0
Requires-Dist: openai>=1.57.0
Requires-Dist: python-dotenv>=1.0.1
Requires-Dist: requests>=2.32.3
